GCoreAPI/GCore_Base.py
GCoreAPI/__init__.py
GCoreAPI/gcore.py
GCoreAPI/gcore_flavors_api.py
GCoreAPI/gcore_floatingips_api.py
GCoreAPI/gcore_instances_api.py
GCoreAPI/gcore_loadbalancers_api.py
GCoreAPI/gcore_networks_api.py
GCoreAPI/gcore_regions_api.py
GCoreAPI/gcore_reserved_fixed_ips_api.py
GCoreAPI/gcore_routers_api.py
GCoreAPI/gcore_subnets_api.py
GCoreAPI/gcore_useractions_api.py
GCoreAPI/gcore_volumes_api.py
GCoreAPI-0.11.dist-info/LICENSE
GCoreAPI-0.11.dist-info/METADATA
GCoreAPI-0.11.dist-info/WHEEL
GCoreAPI-0.11.dist-info/top_level.txt
GCoreAPI-0.11.dist-info/RECORD
